{"Shopping-Shopping": 0, "Shopping-Grocery": 0, "Shopping-Tools": 0, "Shopping-Garden": 0, "Shopping-Furniture": 0, "Shopping-Home": 0, "Shopping-Electronics": 0, "Shopping-Office Supplies": 0, "Shopping-Books": 0, "Shopping-Movies": 0, "Shopping-Music": 0, "Shopping-Games": 0, "Shopping-Toys": 0, "Shopping-Baby": 0, "Shopping-Clothes": 0, "Shopping-Shoes": 0, "Personal-Personal": 0, "Personal-General": 0, "Personal-Gym": 0, "Personal-Hair": 0, "Personal-Cosmetics": 0, "Personal-Baby": 0, "Personal-Entertainment": 0, "Food-Food": 0, "Food-Fast Food": 0, "Food-Dining": 0, "Food-Delivery": 0, "Online-Online": 0, "Online-Subscriptions": 0, "Online-Services": 0, "Online-Shopping": 0, "Online-Games": 0, "Bills-Bills": 0, "Bills-Electric": 0, "Bills-Water": 0, "Bills-Internet": 0, "Bills-Phone": 0, "Bills-Cable": 0, "Bills-Other": 0, "Medical-Medical": 0, "Medical-Primary Care": 0, "Medical-Dental": 0, "Medical-Specialty Care": 0, "Medical-Urgent Care": 0, "Medical-Medications": 0, "Medical-Medical Devices": 0, "Medical-Mental": 0, "Insurance-Insurance": 0, "Insurance-Home": 0, "Insurance-Auto": 0, "Insurance-Life": 0, "Insurance-Renter": 0, "Insurance-Disability": 0, "Insurance-Other": 0, "Home-Home": 0, "Home-Rent": 0, "Home-Repairs": 0, "Home-HOA Fees": 0, "Home-Taxes": 0, "Savings Deposit-Savings Deposit": 0, "Savings Deposit-General": 0, "Savings Deposit-Emergency": 0, "Savings Deposit-Retirement": 0, "Savings Deposit-Investments": 0, "Savings Withdraw-Savings Withdraw": 0, "Savings Withdraw-General": 0, "Savings Withdraw-Emergency": 0, "Savings Withdraw-Retirement": 0, "Savings Withdraw-Investments": 0, "Transportation-Transportation": 0, "Transportation-Car": 0, "Transportation-Gas": 0, "Transportation-Repairs": 0, "Transportation-Parking": 0, "Transportation-Registration": 0, "Transportation-Bus": 0, "Transportation-Train": 0, "Transportation-Plane": 0, "Debt-Debt": 0, "Debt-General": 0, "Debt-Personal Loan": 0, "Debt-Student Loan": 0, "Debt-Credit Card": 0, "Debt-Auto": 0, "Debt-Mortgage": 0, "Loan-Loan": 0, "Loan-General": 0, "Loan-Personal Loan": 0, "Loan-Student Loan": 0, "Loan-Credit Card": 0, "Loan-Auto": 0, "Loan-Mortgage": 0, "Entertainment-Entertainment": 0, "Entertainment-Alcohol": 0, "Entertainment-Drugs": 0, "Entertainment-Dating": 0, "Entertainment-Gambling": 0, "Travel-Travel": 0, "Travel-General": 0, "Travel-Concerts": 0, "Travel-Business": 0, "Travel-Vacation": 0, "Other Expenses-Other Expenses": 0, "Other Expenses-Other": 0, "Other Expenses-One Time": 0, "Other Expenses-Gifts": 0, "Other Expenses-Donations": 0, "Other Expenses-Transfer": 0, "Other Expenses-Cash": 0, "Other Expenses-Fees": 0, "Misc-Misc": 0, "Misc-Bank Verification": 0, "Misc-Credit Repayment": 0, "Misc-Other": 0, "Income-Income": 0, "Income-Gifts": 0, "Income-Dividends": 0, "Income-Paycheck": 1000, "Income-Bonus": 0, "Income-Interest": 0, "Income-Refunds": 0, "Income-Reimbursements": 0, "Income-Rental": 0, "Income-Transfer": 0, "Income-Cash Deposit": 0, "Income-Other": 0, "Food-Dessert": 0, "Food-Festivals": 0}